{"links":[{"source":"buying","target":"unacceptable","value":"0.424354|2"},{"source":"buying","target":"1","value":"-0.090029|1"},{"source":"buying","target":"good","value":"-0.806014|2"},{"source":"buying","target":"8","value":"-0.018488|1"},{"source":"buying","target":"very good","value":"-0.356438|3"},{"source":"buying","target":"5","value":"0.117028|3"},{"source":"buying","target":"11","value":"-0.014202|2"},{"source":"buying","target":"0","value":"-0.271753|3"},{"source":"buying","target":"6","value":"-0.001124|2"},{"source":"buying","target":"10","value":"0.745633|4"},{"source":"maint","target":"10","value":"0.003771|2"},{"source":"maint","target":"3","value":"-1.000000|2"},{"source":"maint","target":"very good","value":"-0.489723|1"},{"source":"maint","target":"unacceptable","value":"0.406204|3"},{"source":"maint","target":"0","value":"0.237592|4"},{"source":"maint","target":"good","value":"0.151408|3"},{"source":"maint","target":"2","value":"0.001105|3"},{"source":"maint","target":"14","value":"0.049918|1"},{"source":"doors","target":"11","value":"0.016830|2"},{"source":"doors","target":"3","value":"0.078219|1"},{"source":"doors","target":"good","value":"-0.169975|2"},{"source":"doors","target":"9","value":"-0.147526|4"},{"source":"doors","target":"14","value":"0.245627|2"},{"source":"persons","target":"good","value":"-0.128215|3"},{"source":"persons","target":"3","value":"-0.220273|1"},{"source":"persons","target":"very good","value":"0.010693|4"},{"source":"persons","target":"11","value":"0.108000|3"},{"source":"persons","target":"acceptable","value":"0.301524|3"},{"source":"lug_boot","target":"13","value":"-0.040395|1"},{"source":"lug_boot","target":"9","value":"-0.004160|3"},{"source":"lug_boot","target":"11","value":"0.009496|1"},{"source":"lug_boot","target":"very good","value":"-0.156676|4"},{"source":"lug_boot","target":"7","value":"0.122018|2"},{"source":"lug_boot","target":"12","value":"-0.158342|3"},{"source":"safety","target":"acceptable","value":"0.583568|4"},{"source":"safety","target":"3","value":"0.152645|3"},{"source":"safety","target":"11","value":"-0.019942|4"},{"source":"safety","target":"0","value":"-0.014221|1"},{"source":"safety","target":"very good","value":"0.339632|2"},{"source":"0","target":"3","value":"0.049446|3"},{"source":"1","target":"0","value":"0.078836|2"},{"source":"1","target":"1","value":"-0.073937|2"},{"source":"1","target":"6","value":"-0.036415|2"},{"source":"2","target":"unacceptable","value":"0.103797|2"},{"source":"2","target":"4","value":"-0.007653|3"},{"source":"3","target":"0","value":"0.009452|4"},{"source":"4","target":"good","value":"-0.013742|3"},{"source":"5","target":"unacceptable","value":"0.055676|4"},{"source":"5","target":"13","value":"-0.005492|3"},{"source":"5","target":"good","value":"0.016516|2"},{"source":"6","target":"1","value":"-0.004232|3"},{"source":"7","target":"14","value":"0.106145|1"},{"source":"7","target":"7","value":"0.068229|4"},{"source":"8","target":"acceptable","value":"-0.017302|2"},{"source":"8","target":"very good","value":"-0.030015|3"},{"source":"9","target":"10","value":"-0.004680|1"},{"source":"10","target":"8","value":"0.150716|2"},{"source":"11","target":"1","value":"0.004536|3"},{"source":"12","target":"very good","value":"-0.057252|3"},{"source":"12","target":"good","value":"-0.050560|2"},{"source":"13","target":"14","value":"0.067338|3"},{"source":"13","target":"7","value":"0.108157|2"},{"source":"13","target":"acceptable","value":"-0.046203|3"},{"source":"14","target":"very good","value":"0.011694|3"}],"nodes":[{"color":"#000","group":"input","id":"buying","name":"buying","pos":0},{"color":"#000","group":"input","id":"maint","name":"maint","pos":1},{"color":"#000","group":"input","id":"doors","name":"doors","pos":2},{"color":"#000","group":"input","id":"persons","name":"persons","pos":3},{"color":"#000","group":"input","id":"lug_boot","name":"lug_boot","pos":4},{"color":"#000","group":"input","id":"safety","name":"safety","pos":5},{"color":"#0000FF","group":"deep","id":"0","name":"0"},{"color":"#0000FF","group":"deep","id":"1","name":"1"},{"color":"#0000FF","group":"deep","id":"2","name":"2"},{"color":"#0000FF","group":"deep","id":"3","name":"3"},{"color":"#0000FF","group":"deep","id":"4","name":"4"},{"color":"#0000FF","group":"deep","id":"5","name":"5"},{"color":"#0000FF","group":"deep","id":"6","name":"6"},{"color":"#0000FF","group":"deep","id":"7","name":"7"},{"color":"#0000FF","group":"deep","id":"8","name":"8"},{"color":"#0000FF","group":"deep","id":"9","name":"9"},{"color":"#0000FF","group":"deep","id":"10","name":"10"},{"color":"#0000FF","group":"deep","id":"11","name":"11"},{"color":"#0000FF","group":"deep","id":"12","name":"12"},{"color":"#0000FF","group":"deep","id":"13","name":"13"},{"color":"#0000FF","group":"deep","id":"14","name":"14"},{"color":"#000","group":"output","id":"unacceptable","name":"unacceptable","pos":0},{"color":"#000","group":"output","id":"acceptable","name":"acceptable","pos":1},{"color":"#000","group":"output","id":"good","name":"good","pos":2},{"color":"#000","group":"output","id":"very good","name":"very good","pos":3}]}